{
    "丁子蘭坑溪": [],
    "七家灣溪": [],
    "七股溪": [],
    "三光溪": [],
    "三坑溪": [],
    "三壘溪": [],
    "三富溪": [],
    "三峽溪": [],
    "三張廍溪": [],
    "三棧溪": [],
    "三爺宮溪": [],
    "三爺溪": [],
    "三疊溪": [],
    "三目溪": [],
    "三笠溪": [],
    "三股子溪": [],
    "三重溪": [],
    "上坪溪": [],
    "上大溪": [],
    "上石頭溪": [],
    "下員坑溪": [],
    "下寮溪": [],
    "下後壁溪": [],
    "下石頭溪": [],
    "下過溪": [],
    "下雙溪": [],
    "中圳溪": [],
    "中坑溪": [],
    "中埔溪": [],
    "中大溪": [],
    "中崙溪": [],
    "中平溪": [],
    "中心崙坑溪": [],
    "中港溪": [],
    "中溪": [],
    "中野溪": [],
    "中間溪": [],
    "丸田溪": [],
    "丹大溪": [],
    "九岸溪": [],
    "九棚溪": [],
    "九芎坑溪": [],
    "乾溪": [],
    "乾華溪": [],
    "二仁溪": [],
    "二林溪": [],
    "二溪": [],
    "二甲溪": [],
    "二重溪": [],
    "二鬮溪": [],
    "五十溪": [],
    "五帝廟溪": [],
    "五里林溪": [],
    "五重溪": [],
    "仙草埔溪": [],
    "伊卡帕南溪": [],
    "佳冬溪": [],
    "保力溪": [],
    "保長坑溪": [],
    "倒孔山溪": [],
    "光復溪": [],
    "兔子坑溪": [],
    "內大溪": [],
    "內寮溪": [],
    "內林溪": [],
    "內湖仔溪": [],
    "內溝溪": [],
    "內田子溪": [],
    "內茅埔溪": [],
    "內雙溪": [],
    "八掌溪": [],
    "八甲溪": [],
    "八蓮溪": [],
    "八連溪": [],
    "八里溪": [],
    "公館溪": [],
    "六股溪": [],
    "六重溪": [],
    "典寶溪": [],
    "冬山河": [],
    "冷水坑溪": [],
    "出水溪": [],
    "利嘉溪": [],
    "前鎮河": [],
    "劍文溪": [],
    "力力溪": [],
    "加典溪": [],
    "加納富溪": [],
    "加蘭溪": [],
    "加走寮溪": [],
    "加都魯溪": [],
    "加里洞溪": [],
    "加鹿溪": [],
    "匏仔寮溪": [],
    "北勢坑溪": [],
    "北勢溪": [],
    "北勢窩溪": [],
    "北坑溪": [],
    "北峰溪": [],
    "北清水溪": [],
    "北港溪": [],
    "北溝溪": [],
    "北溪": [],
    "北絲鬮溪": [],
    "北頭溪": [],
    "匹亞桑溪": [],
    "十九份溪": [],
    "十八份溪": [],
    "十八重溪": [],
    "十里溪": [],
    "卑南大溪": [],
    "卑南溪": [],
    "卓棍溪": [],
    "卓溪": [],
    "南勢湖溪": [],
    "南勢溪": [],
    "南坑溪": [],
    "南山溪": [],
    "南崁溪": [],
    "南庄溪": [],
    "南河溪": [],
    "南清水溝溪": [],
    "南清水溪": [],
    "南港溪": [],
    "南湖溪": [],
    "南溪": [],
    "南澳北溪": [],
    "南澳南溪": [],
    "南澳溪": [],
    "南靖溪": [],
    "卡拉模基溪": [],
    "卡社溪": [],
    "友蚋溪": [],
    "口隘溪": [],
    "叭嗹港溪": [],
    "吉安溪": [],
    "后壁溪": [],
    "吧沙加魯溪": [],
    "呂範溪": [],
    "和平北溪": [],
    "和平南溪": [],
    "和平溪": [],
    "和社溪": [],
    "咬狗溪": [],
    "哈盆溪": [],
    "員潭溪": [],
    "啞口坑溪": [],
    "喜樹仔港溪": [],
    "嘉寶溪": [],
    "嘉武溪": [],
    "嘉興溪": [],
    "嘉豐一號溪": [],
    "嘉豐二號溪": [],
    "嘉豐溪": [],
    "四分溪": [],
    "四季郎溪": [],
    "四重溪": [],
    "圓山溪": [],
    "圓潭溪": [],
    "土場溪": [],
    "土庫溪": [],
    "坑仔內小溪": [],
    "坑子溪": [],
    "坤溪": [],
    "坪溪": [],
    "城埔溪": [],
    "埔坪溪": [],
    "埔心溪": [],
    "基隆河": [],
    "塔克金溪": [],
    "塔寮坑溪": [],
    "塔瓦溪": [],
    "塔羅灣溪": [],
    "士文溪": [],
    "壽豐溪": [],
    "外大溪": [],
    "外股溪": [],
    "外雙溪": [],
    "多望溪": [],
    "大內坑溪": [],
    "大南澳溪": [],
    "大和溪": [],
    "大坑溪": [],
    "大坡溪": [],
    "大坪溪": [],
    "大埔溪": [],
    "大堀溪": [],
    "大安溪": [],
    "大富溪": [],
    "大屯溪": [],
    "大嵙崁溪": [],
    "大庄溪": [],
    "大德溪": [],
    "大林溪": [],
    "大梅溪": [],
    "大檜溪": [],
    "大武崙溪": [],
    "大武溪": [],
    "大清水溪": [],
    "大湖口溪": [],
    "大湖溪": [],
    "大溪": [],
    "大溪墘溪": [],
    "大漢溪": [],
    "大甲溪": [],
    "大礁溪": [],
    "大窠坑溪": [],
    "大竹溪": [],
    "大羅南溪": [],
    "大羅蘭溪": [],
    "大肚溪": [],
    "大肚滑溪": [],
    "大股溪": [],
    "大興溪": [],
    "大豹溪": [],
    "大里溪": [],
    "大雪溪": [],
    "天狗溪": [],
    "太多蘭溪": [],
    "太平溪": [],
    "太麻里溪": [],
    "安朔溪": [],
    "安泰溪": [],
    "安農溪": [],
    "安通溪": [],
    "官田溪": [],
    "宜蘭河": [],
    "客雅溪": [],
    "密枝溪": [],
    "富家溪": [],
    "富林溪": [],
    "富源溪": [],
    "富興溪": [],
    "寒死人溪": [],
    "寒溪": [],
    "寧埔溪": [],
    "寶來溪": [],
    "寶斗溪": [],
    "將軍溪": [],
    "尋腰溪": [],
    "小坑仔溪": [],
    "小坑溪": [],
    "小溪": [],
    "小礁溪": [],
    "小路溪": [],
    "尖仔鹿溪": [],
    "尖山溪": [],
    "尖山腳溪": [],
    "屈尺溪": [],
    "山溪": [],
    "山貓仔溪": [],
    "山里一號溪": [],
    "山里溪": [],
    "山間溪": [],
    "岡山溪": [],
    "峨嵋溪": [],
    "島榕溪": [],
    "崁仔腳溪": [],
    "崁腳": [],
    "崁頂溪": [],
    "崁頭溪": [],
    "崎腳溪": [],
    "崙埤溪": [],
    "崙天溪": [],
    "崙子溪": [],
    "巒大溪": [],
    "布蓬溪": [],
    "平廣溪": [],
    "平林溪": [],
    "平溪": [],
    "康誥坑溪": [],
    "廍子溪": [],
    "彼爿溪": [],
    "後勁溪": [],
    "後坑溪": [],
    "後堀溪": [],
    "後壁溪": [],
    "後寮溪": [],
    "後州溪": [],
    "後旦溪": [],
    "後溪": [],
    "後番仔坑溪": [],
    "後龍溪": [],
    "得子口溪": [],
    "德慶溪": [],
    "德盛溪": [],
    "德荃溪": [],
    "志樂溪": [],
    "志航溪": [],
    "急水溪": [],
    "愛河": [],
    "成功溪": [],
    "房裡溪": [],
    "打哪叭溪": [],
    "打巴溪": [],
    "打狗溪": [],
    "打馬溝溪": [],
    "拉庫散溪": [],
    "拔下二溪": [],
    "拔仔崗溪": [],
    "拔西猴溪": [],
    "指南溪": [],
    "排谷溪": [],
    "排骨溪": [],
    "摸乳巷坑溪": [],
    "文蘭溪": [],
    "文里溪": [],
    "斯可野溪": [],
    "新厝仔溪": [],
    "新城溪": [],
    "新埤溪": [],
    "新屋溪": [],
    "新庄子溪": [],
    "新店溪": [],
    "新武呂溪": [],
    "新港溪": [],
    "新虎尾溪": [],
    "新街溪": [],
    "新豐溪": [],
    "施厝寮溪": [],
    "旗山溪": [],
    "日新溪": [],
    "早溪": [],
    "旭海溪": [],
    "旱溪": [],
    "旺萊溪": [],
    "昇高溪": [],
    "普幹溪": [],
    "景山溪": [],
    "景美溪": [],
    "智慧溪": [],
    "暖暖溪": [],
    "曾文溪": [],
    "月桃溪": [],
    "望溪": [],
    "朝庸溪": [],
    "木坑溪": [],
    "木板溪": [],
    "木瓜溪": [],
    "札孔溪": [],
    "朴子溪": [],
    "東埔蚋溪": [],
    "東壘溪": [],
    "東山溪": [],
    "東廣寮溪": [],
    "東河溪": [],
    "東港溪": [],
    "東溪": [],
    "東澳溪": [],
    "松子腳溪": [],
    "松羅溪": [],
    "枋山溪": [],
    "枋脚溪": [],
    "林口溪": [],
    "林子溪": [],
    "林祿溪": [],
    "林邊溪": [],
    "柑仔坑溪": [],
    "柯仔湖溪": [],
    "柯子湖溪": [],
    "柴頭港溪": [],
    "桶後溪": [],
    "梵梵溪": [],
    "楊厝溪": [],
    "楓林溪": [],
    "楓港溪": [],
    "楓溪": [],
    "楠梓仙溪": [],
    "楠梓溪": [],
    "楠溪": [],
    "樂合溪": [],
    "樂和溪": [],
    "樂樂溪": [],
    "樟平溪": [],
    "樟樹溪": [],
    "樹梅坑溪": [],
    "橫流溪": [],
    "橫溪": [],
    "檳榔坑溪": [],
    "欖仁溪": [],
    "武洛溪": [],
    "武鹿溪": [],
    "死溪": [],
    "殺蛇溪": [],
    "水仙溪": [],
    "水母溪": [],
    "水璉溪": [],
    "水碓窠溪": [],
    "水里溪": [],
    "水長流溪": [],
    "永定溪": [],
    "汶水溪": [],
    "沄水溪": [],
    "沙河溪": [],
    "沙灣溪": [],
    "沙里仙溪": [],
    "河內溪": [],
    "油羅溪": [],
    "油車溪": [],
    "泥水溪": [],
    "泰崗溪": [],
    "洋仔厝溪": [],
    "津林溪": [],
    "洪荒溪": [],
    "洽溪": [],
    "海尾溪": [],
    "海豐崙溪": [],
    "淡水河": [],
    "深坑子溪": [],
    "深坑溪": [],
    "深澳坑溪": [],
    "清水溪": [],
    "清流溪": [],
    "清溪": [],
    "港口溪": [],
    "港子溪": [],
    "港尾子溪": [],
    "溪尾寮溪": [],
    "溫寮溪": [],
    "漁人溪": [],
    "漚汪溪": [],
    "澐水溪": [],
    "濁口溪": [],
    "濁水坑溪": [],
    "濁水溪": [],
    "灣丘溪": [],
    "灣潭溪": [],
    "火燒寮坑溪": [],
    "灰寮溪": [],
    "烏塗溪": [],
    "烏月溪": [],
    "烏溪": [],
    "烏牛欄溪": [],
    "烏石坑溪": [],
    "烏紗溪": [],
    "烏萬溪": [],
    "無名溪": [],
    "牛埔溪": [],
    "牛稠埔坑溪": [],
    "牛稠埔溪": [],
    "牛稠溪": [],
    "牛角灣溪": [],
    "牡丹溪": [],
    "犁頭山溪": [],
    "猴洞坑溪": [],
    "獅子頭溪": [],
    "率芒溪": [],
    "玉峰溪": [],
    "班芝埔溪": [],
    "瑞樹坑溪": [],
    "瑪鍊溪": [],
    "瑪陵坑溪": [],
    "瓏狸溪": [],
    "瓦窯溪": [],
    "田心子溪": [],
    "留茂安溪": [],
    "番子寮溪": [],
    "番子路科溪": [],
    "白樹腳溪": [],
    "白水溪": [],
    "白沙彌溪": [],
    "白石溪": [],
    "白米溪": [],
    "百字坑溪": [],
    "眉溪": [],
    "知本溪": [],
    "石公溪": [],
    "石厝坑溪": [],
    "石坑溪": [],
    "石壁坑溪": [],
    "石子坑溪": [],
    "石山溪": [],
    "石崩山溪": [],
    "石榴班溪": [],
    "石牛溪": [],
    "石盤溪": [],
    "石硦溪": [],
    "石硿子溪": [],
    "石碇溪": [],
    "石門溪": [],
    "石頭溪": [],
    "石龜溪": [],
    "石𥕢溪": [],
    "破鐺溪": [],
    "碧水溪": [],
    "碼崙溪": [],
    "磨刀溪": [],
    "磺港溪": [],
    "磺溪": [],
    "礁溪": [],
    "社子溪": [],
    "福德溪": [],
    "福興溪": [],
    "禮門溪": [],
    "秀姑巒溪": [],
    "秀巒溪": [],
    "立霧溪": [],
    "竹坑溪": [],
    "竹子港溪": [],
    "竹崙溪": [],
    "竹湖溪": [],
    "竹溪": [],
    "竹社溪": [],
    "竿林溪": [],
    "筆石溪": [],
    "筏子溪": [],
    "粗坑溪": [],
    "粗溪": [],
    "紅水仙溪": [],
    "紅石溪": [],
    "紅葉溪": [],
    "羅東溪": [],
    "羅莫溪": [],
    "美優溪": [],
    "美崙溪": [],
    "美濃溪": [],
    "老佛溪": [],
    "老坑溪": [],
    "老崩山溪": [],
    "老庄溪": [],
    "老梅溪": [],
    "老泉溪": [],
    "老濃溪": [],
    "老田寮溪": [],
    "老街溪": [],
    "興仁溪": [],
    "舊溪": [],
    "舊濁水溪": [],
    "舊虎尾溪": [],
    "舊鹽埕溪": [],
    "芭蕉溪": [],
    "花蓮溪": [],
    "苑裡溪": [],
    "苓仔溪": [],
    "茂安溪": [],
    "茄苳溪": [],
    "草埔尾溪": [],
    "草山溪": [],
    "草湖溪": [],
    "草濫溪": [],
    "荖寮溪": [],
    "荖溪": [],
    "荖濃溪": [],
    "莫溪": [],
    "莿桐脚溪": [],
    "菜寮溪": [],
    "華綠溪": [],
    "萬大溪": [],
    "萬安溪": [],
    "萬寮溪": [],
    "萬年松溪": [],
    "萬年溪": [],
    "萬里溪": [],
    "萬順溪": [],
    "蒼庫溪": [],
    "蓬萊坑溪": [],
    "蕃寮溪": [],
    "蕃薯寮坑溪": [],
    "蘇澳溪": [],
    "蘭陽溪": [],
    "虎尾溪": [],
    "虎頭溪": [],
    "螺仔溪": [],
    "西勢溪": [],
    "西湖溪": [],
    "西溪": [],
    "西片溪": [],
    "觀音坑溪": [],
    "觀音溪": [],
    "許縣溪": [],
    "豆子埔溪": [],
    "豐坪溪": [],
    "豐濱溪": [],
    "貓羅溪": [],
    "貴子坑溪": [],
    "賴仲坑溪": [],
    "赤蘭溪": [],
    "軋孔溪": [],
    "軟埤溪": [],
    "通霄溪": [],
    "連溪": [],
    "過溪": [],
    "達仁溪": [],
    "那菝林溪": [],
    "郡坑溪": [],
    "郡大溪": [],
    "都威溪": [],
    "都老老恩溪": [],
    "都蘭溪": [],
    "里仁溪": [],
    "金包里溪": [],
    "金崙溪": [],
    "金瓜寮溪": [],
    "金面溪": [],
    "銅文蘭溪": [],
    "長濱溪": [],
    "關渡溪": [],
    "阿公店溪": [],
    "阿夜西溪": [],
    "阿拔泉溪": [],
    "阿柔溪": [],
    "阿眉溪": [],
    "阿美溪": [],
    "阿里不動溪": [],
    "阿里山溪": [],
    "阿里磅溪": [],
    "阿里荖溪": [],
    "陳厝坑溪": [],
    "陳有蘭溪": [],
    "隆隆溪": [],
    "隘寮北溪": [],
    "隘寮南溪": [],
    "隘寮溪": [],
    "雙溪": [],
    "雞柔溪": [],
    "雞隆河": [],
    "雪山坑溪": [],
    "雪山溪": [],
    "雲林溪": [],
    "雷公坑溪": [],
    "電光一號溪": [],
    "電光二號溪": [],
    "霄裡溪": [],
    "霞喀羅溪": [],
    "青潭溪": [],
    "青蕃溪": [],
    "頂坑溪": [],
    "頂埔溪": [],
    "頂寮溪": [],
    "頂後壁溪": [],
    "頂石頭溪": [],
    "頂粗坑溪": [],
    "頂過溪": [],
    "頭前溪": [],
    "頭城溪": [],
    "頭汴坑溪": [],
    "頭重溪": [],
    "飛砂溪": [],
    "飛鳳溪": [],
    "食水嵙溪": [],
    "馬佛溪": [],
    "馬加祿溪": [],
    "馬太鞍溪": [],
    "馬岸溪": [],
    "馬武溪": [],
    "馬海溪": [],
    "馬達拉溪": [],
    "馬遠溪": [],
    "馬里闊丸溪": [],
    "高寮溪": [],
    "高屏溪": [],
    "高雄農場": [],
    "魚寮溪": [],
    "鰲溪": [],
    "鱉溪": [],
    "鳳山溪": [],
    "鳳林溪": [],
    "鳳溪": [],
    "鶯歌溪": [],
    "鹽水坑溪": [],
    "鹽水港溪": [],
    "鹽水溪": [],
    "鹽港溪": [],
    "鹿寮仔溪": [],
    "鹿寮坑溪": [],
    "鹿寮溪": [],
    "鹿耳門溪": [],
    "鹿野溪": [],
    "鹿鳴溪": [],
    "麗太溪": [],
    "龍宮溪": [],
    "龍溪": [],
    "龜重溪": [],
    "𩻸魚堀溪": []
}