{
    "驪山老母": [],
    "觀音佛祖大眾爺": [],
    "觀音三菩薩": [],
    "觀音三佛祖": [],
    "觀世音菩薩": ["觀世音", "觀音大士", "觀音佛祖", "觀音菩薩"],
    "觀世音佛祖": [],
    "靈寶天尊": [],
    "靈應公": [],
    "靈宮王天君": [],
    "靈官大帝": [],
    "靈安尊王": [],
    "靈母娘娘": [],
    "靈台公": [],
    "靈山老母": [],
    "靈山王母娘娘": [],
    "灝府千歲": [],
    "顯靈五帝": [],
    "顯濟靈王": [],
    "顯應祖師": [],
    "酈府王爺": [],
    "顧夫人媽": [],
    "酆都大帝": [],
    "護國尊王": [],
    "護國城隍老爺": ["護國城隍"],
    "護界聖帝": [],
    "騰風元帥": [],
    "釋迦摩尼佛": ["釋迦佛祖", "釋迦佛", "釋迦牟尼佛", "釋迦如來佛祖"],
    "蘇秦李王爺": [],
    "蘇府梁王爺": [],
    "蘇府王爺": [],
    "蘇府元帥": [],
    "蘇府大王爺": [],
    "蘇府千歲": [],
    "蘇府三王爺": [],
    "蘇府二王爺": [],
    "蘇李池三府王爺": [],
    "蘇王爺": [],
    "蘇大王爺": [],
    "爐公先師": [],
    "寶聖王佛": [],
    "麗伯公": [],
    "關基廟主": [],
    "關帝聖君": ["關聖帝", "關帝爺", "關帝君", "關二爺", "關聖帝君"],
    "關呂張三聖": [],
    "藥王大帝": [],
    "羅府千歲": [],
    "羅周千歲": [],
    "羅安公": [],
    "魏將軍": [],
    "魏姑娘": [],
    "魏王爺": [],
    "騎虎尊王": [],
    "鎮殿五府千歲": [],
    "鎮國將軍": [],
    "鎮海將軍": [],
    "鎮海元帥": [],
    "鎮海五元帥": [],
    "鎮山城隍爺": [],
    "鎮山元帥": [],
    "轉輪聖王": [],
    "豐都大帝": [],
    "瞿公真人": [],
    "鴻鈞老祖": [],
    "韓愈": [],
    "韓府王爺": [],
    "韓府千歲": [],
    "霞海城隍尊神": ["霞海城隍尊師", "霞海城隍公祖", "霞海城隍"],
    "鍾馗": [],
    "豁落靈官王天君": ["豁落靈官"],
    "謝映登仙翁": [],
    "謝府王爺": [],
    "謝府王公": [],
    "謝府元帥": [],
    "謝府五元帥": [],
    "謝府大元帥": [],
    "謝府千歲": [],
    "謝安王": [],
    "謝安公": [],
    "謝元帥": [],
    "薜府王爺": ["薛府王爺"],
    "薛府元帥": [],
    "薛府千歲": [],
    "薛巡王爺": [],
    "薛玉聖媽": [],
    "薛王爺": [],
    "薛仁貴千歲": [],
    "薛千歲": [],
    "舉人公": [],
    "臨水夫人陳靖姑": [],
    "臨水夫人": [],
    "禪師菩薩": [],
    "濟世光耀大帝李觀濤": [],
    "濟公禪師":["濟公菩薩", "濟公活佛", "濟公佛祖", "濟公仙師", "濟公"],
    "檨仔王": [],
    "戴府王爺": [],
    "戴代王": [],
    "應公應媽": [],
    "彌勒尊佛": ["彌勒祖師", "彌勒佛"],
    "彌天老母": [],
    "龍樹尊王": [],
    "龍德星君": [],
    "龍府元帥": [],
    "龍府千歲": [],
    "龍君帝君": [],
    "隨駕王爺李勇": [],
    "隨駕王爺玄天上帝": [],
    "隨身大將軍": [],
    "閻羅天子包青天": [],
    "閻羅天子大天尊仙佛": [],
    "蕭潘郭三府王爺": [],
    "蕭府王爺": [],
    "蕭府太傅": [],
    "蕭府公祖": [],
    "蕭府大帝": [],
    "蕭府千歲": [],
    "蕭太傅": [],
    "蕭大哥": [],
    "縣城隍": [],
    "盧聖伯公": [],
    "盧府千歲": [],
    "盧王千歲": [],
    "盧三公": [],
    "燃燈佛": [],
    "樹德尊王": [],
    "樹德元帥": [],
    "樹王公": [],
    "學法祖師公": [],
    "凝陽帝君": [],
    "黎山老母": [],
    "魯班先師": [],
    "魯班公": [],
    "閰羅天子": [],
    "閭山張公法王": [],
    "閭山法主": [],
    "閭山三位祖師": [],
    "閭山三元張公法主聖君": [],
    "鄭新登公": [],
    "鄭府聖侯": [],
    "鄭成功王爺": [],
    "鄭成功": [],
    "鄭夫人媽": [],
    "鄭元帥": [],
    "鄧府天神": [],
    "諸府千歲": [],
    "褔德正神": [],
    "褒忠義民爺": [],
    "褒忠義民": [],
    "褒忠義士高顯爺尊神": [],
    "蔭林祖師": [],
    "蔡媽娘娘": [],
    "蔡婆主帥": [],
    "蔡府王爺": [],
    "蔡府元帥": [],
    "蔡府千歲": [],
    "蔡仙姑": [],
    "蓮城佛祖": [],
    "蓮花菩薩": [],
    "磐古聖帝": [],
    "盤古萬歲": [],
    "盤古聖帝": [],
    "盤古爺": [],
    "盤古開天祖": [],
    "盤古開天王": [],
    "盤古祖師": [],
    "盤古帝王": [],
    "盤古公": [],
    "潘府王爺": [],
    "樟仙師": [],
    "槺榔公": [],
    "敵天大帝": [],
    "廣濟禪師": [],
    "廣澤童子": [],
    "廣澤尊王": [],
    "廣澤保安尊王": [],
    "廣惠聖王": [],
    "廣惠尊者": [],
    "廣惠尊王": [],
    "廣信天師": [],
    "厲王爺": [],
    "劍童公": [],
    "劉國公": [],
    "劉海蟾祖師": [],
    "劉府仙公": [],
    "劉府王爺": [],
    "劉府王公": [],
    "劉府元帥": [],
    "劉府千歲": [],
    "劉仙姑": [],
    "劉王李府三尊王": [],
    "劉公聖君": [],
    "齊天大聖大天尊": [],
    "齊天大聖": [],
    "鳳凰母娘": [],
    "魁星夫子": [],
    "魁星大帝": [],
    "輔順將軍": [],
    "輔信王公": [],
    "趙聖帝君": [],
    "趙府元帥": [],
    "趙府千歲": [],
    "趙公明元帥": [],
    "趙公明": [],
    "趙元帥": [],
    "趙子龍": [],
    "趙大王": [],
    "裴先帥": [],
    "蒼天上帝": [],
    "福德爺公": [],
    "福德爺": [],
    "福德正神土地公": [],
    "福德正神": [],
    "福神像": [],
    "福神正神": [],
    "福州聖母": [],
    "福王老爺": [],
    "福王千歲": [],
    "碧霞元君": [],
    "瑤池金母娘娘": [],
    "瑤池金母大天尊": [],
    "瑤池金母": [],
    "瑤池西王金母大天尊": [],
    "瑤池西王金母": [],
    "漁師爺": [],
    "榮府王爺": [],
    "慚愧祖師公": [],
    "慚愧祖師": [],
    "廖先生公": [],
    "寧靖王": [],
    "境主爺": [],
    "境主尊神": [],
    "靖惠侯敦仁公": [],
    "靖忠元帥": [],
    "雷府大將爺": [],
    "雷府大將公": [],
    "雷府大將": [],
    "雷府千歲": [],
    "雷朱薛刑四府王爺": [],
    "雷王爺": [],
    "鄔府千歲": [],
    "達摩祖師": [],
    "道濟禪師": [],
    "道濟先師": [],
    "道濟古佛": [],
    "道濟仙師": [],
    "道德天尊": [],
    "道教神": [],
    "道元祖師爺": [],
    "遊海元帥": [],
    "遊府千歲": [],
    "遊巡七府大王": [],
    "遊巡七王": [],
    "路嬌姑媽": [],
    "詹公聖侯": [],
    "董雙成仙姑": [],
    "董將軍": [],
    "董府千歲": [],
    "董王爺": [],
    "董公真仙迦昆羅王": [],
    "董公真仙": [],
    "董公": [],
    "董元帥爺": [],
    "葉府千歲": [],
    "葉朱李千歲": [],
    "萬靈公": [],
    "萬薛池府王爺": [],
    "萬應媽": [],
    "萬應公爺": [],
    "萬應公媽": [],
    "萬應公祖": [],
    "萬應公": [],
    "萬興公": [],
    "萬壽公": [],
    "萬聖爺": [],
    "萬聖王": [],
    "萬聖公媽": [],
    "萬聖公": [],
    "萬善諸君": [],
    "萬善諸公": [],
    "萬善爺圓仔公": [],
    "萬善爺公": [],
    "萬善爺大將軍": [],
    "萬善爺": [],
    "萬善祠公": [],
    "萬善相公": [],
    "萬善君": [],
    "萬善同歸公": [],
    "萬善同莊永公": [],
    "萬善同公": [],
    "萬善公婆": [],
    "萬善公": [],
    "萬教帝君": [],
    "萬軍主帥": [],
    "萬法祖師": [],
    "萬府王爺": [],
    "萬府千歲": [],
    "萬姓爺": [],
    "萬姓公媽神主牌位": [],
    "萬姓公媽祖": [],
    "萬姓公": [],
    "萬里千君": [],
    "萬年神": [],
    "萬平公": [],
    "萬仙爺公": [],
    "萬仁公": [],
    "萬子姑娘": [],
    "萬士爺": [],
    "萬人爺公": [],
    "聖德元帥": [],
    "聖義元帥": [],
    "聖爺公": [],
    "聖媽": [],
    "聖祖": [],
    "聖侯恩主": [],
    "聖侯公祖": [],
    "聖姑": [],
    "聖母媽祖": [],
    "聖母娘娘": [],
    "聖王公": [],
    "聖公聖媽": [],
    "聖公媽": [],
    "聖公伯": [],
    "聖公": [],
    "聖仁保生大帝": [],
    "義善姑": [],
    "義勇爺": [],
    "義民爺公": [],
    "義民爺": [],
    "義民公": [],
    "義民三公": [],
    "義民": [],
    "義士爺": [],
    "節孝貞烈婦": [],
    "照應神君": [],
    "溫康池王爺": [],
    "溫府王爺": [],
    "溫府元帥": [],
    "溫府千歲": [],
    "溫府七府千歲": [],
    "溫池王爺": [],
    "溫王爺": [],
    "溫王千歲": [],
    "準提菩薩": [],
    "準提佛母": [],
    "歲德民爺": [],
    "楓樹尊王": [],
    "楓府千歲": [],
    "楊府聖王": [],
    "楊府爺": [],
    "楊府真人": [],
    "楊府太師": [],
    "楊府六使": [],
    "楊府元帥": [],
    "楊府大神": [],
    "楊府千歲": [],
    "楊府三大神": [],
    "楊府七千歲": [],
    "楊令公": [],
    "楊太保元帥": [],
    "楊公八使": [],
    "楊五賽元帥": [],
    "慈濟聖母": [],
    "慈聖媽": [],
    "慈善爺": [],
    "感天上帝": [],
    "媽祖娘娘": [],
    "媽祖娘": [],
    "媽祖佛祖": [],
    "媽祖天上聖母": [],
    "媽祖三府千歲": [],
    "媽祖": [],
    "塩糖池": [],
    "圓通自在天尊": [],
    "圓通大士": [],
    "黑旗將軍": [],
    "黑面佛祖": [],
    "黑面北極玄天上帝": [],
    "黑虎大將": [],
    "黑府將軍": [],
    "黑川伯公": [],
    "黃道老仙師": [],
    "黃聖王": [],
    "黃欽府千歲": [],
    "黃將軍": [],
    "黃苗公": [],
    "黃皇聖帝": [],
    "黃帝道祖": [],
    "黃帝": [],
    "黃府王爺": [],
    "黃府太保": [],
    "黃府天使": [],
    "黃府元帥": [],
    "黃府千歲": [],
    "黃府三將軍": [],
    "黃吉公": [],
    "黃玉泰主公": [],
    "黃正公": [],
    "黃元帥": [],
    "黃二大使": [],
    "順興公": [],
    "順府王爺": [],
    "順正府大王公": [],
    "順正大王公": [],
    "順王爺": [],
    "順水媽": [],
    "順天聖母陳靖姑": [],
    "順天聖母": [],
    "順天元帥": [],
    "項羽元帥": [],
    "開蘭吳沙公": [],
    "開閩尊王": [],
    "開臺聖王鄭成功":["開臺聖王"],
    "開漳聖王公":["開漳聖王"],
    "開彰聖王": [],
    "開基聖母": [],
    "開國仙帝": [],
    "開府元帥": [],
    "開台聖王": [],
    "開台尊王": [],
    "開台國聖": [],
    "開台國姓": [],
    "開天萬歲": [],
    "開天聖祖": [],
    "開天聖帝": [],
    "開天炎帝": [],
    "開天仙帝": [],
    "開天大帝": [],
    "開山聖帝君": [],
    "開山聖侯": [],
    "開山聖王": [],
    "開山大帝": [],
    "辜婦媽": [],
    "評周元帥": [],
    "註生娘娘": [],
    "虛空三十六天童": [],
    "華隆仙翁": [],
    "華陀真人":["華陀仙師", "華佗先師"],
    "華光大帝": [],
    "菁埔夫人": [],
    "舜府千歲": [],
    "紫微大帝": [],
    "紫陽朱夫子": [],
    "焦面大士": [],
    "無極濟公活佛": [],
    "無極瑤池金母": [],
    "無極瑤池西王老母": [],
    "無極聖祖": [],
    "無極混玄聖祖": [],
    "無極混元聖祖": [],
    "無極混元玄玄上尊": [],
    "無極混元三聖大天尊": [],
    "無極神母": [],
    "無極原始大天尊": [],
    "無極至尊元始天王": [],
    "無極至尊": [],
    "無極老母娘娘": [],
    "無極老母": [],
    "無極地母大天尊": [],
    "無極玉皇大天至尊": [],
    "無極王母": [],
    "無極太上皇母": [],
    "無極天王": [],
    "無極五母": [],
    "無極小王爺": [],
    "無極三清道祖": [],
    "無上虛空地母慈尊": [],
    "無上虛空地母至尊": [],
    "湘軍劉少斌將軍": [],
    "湄洲聖母": [],
    "湄州天上聖母": [],
    "游府千歲": [],
    "森府王爺": [],
    "棟境公": [],
    "普庵菩薩": [],
    "普庵祖師": [],
    "普庵祖佛": [],
    "普庵真人": [],
    "普庵佛祖": [],
    "普唵祖師": [],
    "普唵佛祖": [],
    "普度公": [],
    "寒單爺": [],
    "善主公": [],
    "勝府元帥": [],
    "陶兵太子": [],
    "陳蕊娘": [],
    "陳靖姑娘娘": [],
    "陳靖姑三姐妹": [],
    "陳靖姑": [],
    "陳聖王宮": [],
    "陳聖王": [],
    "陳聖公": [],
    "陳黃武三王爺": [],
    "陳府城隍": [],
    "陳府夫人": [],
    "陳府元帥": [],
    "陳府二元帥爺公": [],
    "陳府二元帥": [],
    "陳池姜三王爺": [],
    "陳刑科昌文": [],
    "陳奶夫人陳靖姑": [],
    "陳奶夫人": [],
    "陳仙姑": [],
    "陳主帥": [],
    "陳氏娘娘": [],
    "陳夫人": [],
    "陳公協台": [],
    "陳元帥": [],
    "陳乃夫人": [],
    "陰陽公": [],
    "陰林祖師": [],
    "陰那慚愧祖師": [],
    "都城隍尊神": [],
    "都城隍": [],
    "都天靈聖": [],
    "都天聖君": [],
    "都天元帥": [],
    "郭聖王": [],
    "郭府聖王": [],
    "郭府千歲": [],
    "郭王爺": [],
    "郭子儀": [],
    "連奶夫人": [],
    "通府千歲": [],
    "通天教主": [],
    "通天元帥": [],
    "赦府千歲": [],
    "許真人": [],
    "許府大將軍": [],
    "莫府元帥": [],
    "莫府千歲": [],
    "莊奶夫人": [],
    "莊公阿賽之香位": [],
    "莆府千歲": [],
    "荷葉先師": [],
    "荷葉仙師": [],
    "章府王爺": [],
    "章大巡": [],
    "眾陰公": [],
    "清雲萬聖爺": [],
    "清朝末年戰亡官兵": [],
    "清府王爺": [],
    "清水祖師爺": [],
    "清水祖師公": [],
    "清水祖師": [],
    "清水二祖師": [],
    "混元聖祖": [],
    "混元老祖": [],
    "淵府千歲": [],
    "梨山老母": [],
    "梁聖公": [],
    "梁府千歲": [],
    "梁夫人媽": [],
    "救世真人": [],
    "排骨先師": [],
    "張蕭連公聖君": [],
    "張聖真君": [],
    "張聖君": [],
    "張毓大帝": [],
    "張將軍": [],
    "張府厲王": [],
    "張府夫人媽": [],
    "張府天師": [],
    "張府元帥": [],
    "張府千歲": [],
    "張府九千歲": [],
    "張姑婆媽": [],
    "張李莫馬池府千歲": [],
    "張李莫府千歲": [],
    "張巡尊王": [],
    "張巡": [],
    "張吳媽祖": [],
    "張吳二位媽祖": [],
    "張池李王爺": [],
    "張玉姑神像": [],
    "張王": [],
    "張天師大帝": [],
    "張天師": [],
    "張公聖君": [],
    "張公法主聖君": [],
    "張公法主": [],
    "康蘇池府千歲": [],
    "康濟明王": [],
    "康趙溫元帥": [],
    "康趙元帥": [],
    "康府王爺": [],
    "康府元帥": [],
    "康府千歲": [],
    "康天千歲": [],
    "康元帥": [],
    "崗山佛祖": [],
    "崑府千歲": [],
    "將軍爺": [],
    "將軍公": [],
    "國聖爺": [],
    "國聖王": [],
    "國聖公": [],
    "國姓爺鄭成功":["國姓爺", "國姓公"],
    "乾元一炁至上至尊": [],
    "鬼谷子": [],
    "高總管": [],
    "高雄市政府": [],
    "高武大帝": [],
    "高府王爺": [],
    "高府元帥": [],
    "高府千歲": [],
    "馬國公": [],
    "馬府大帝": [],
    "馬府千歲": [],
    "馬府二千歲": [],
    "馬使爺": [],
    "郝府王爺": [],
    "軒轅黃帝": [],
    "財神爺": [],
    "財神王爺": [],
    "財神土地公": [],
    "荊府上帝": [],
    "耿府千歲": [],
    "純陽帝君": [],
    "秦府大帝": [],
    "秦李池三府王爺": [],
    "神龍仙姑": [],
    "神農聖帝":["神農開天炎帝", "神農帝君", "神農炎帝", "神農先帝", "神農大帝"],
    "神武天皇": [],
    "祖師公": [],
    "祖先公": [],
    "真武大帝": [],
    "真君": [],
    "烏面將軍": [],
    "海眾先師": [],
    "海皇天子": [],
    "浮池祖師": [],
    "泰山仙祖": [],
    "泰山": [],
    "殷府王爺": [],
    "殷府三千歲": [],
    "案君元帥": [],
    "校地爺公": [],
    "悟龍師父": [],
    "恩主聖侯": [],
    "恩主公-陳淵": [],
    "恩主公": [],
    "徐媽": [],
    "徐府王爺": [],
    "徐府千歲": [],
    "徐府三千歲": [],
    "徐元帥": [],
    "孫臏祖師": [],
    "孫臏真人": [],
    "孫臏仙師": [],
    "孫將軍": [],
    "孫真人": [],
    "孫府真人": [],
    "孫千帥": [],
    "娘媽": [],
    "哪吒太子": [],
    "哪吒三太子": [],
    "原始道德天尊": [],
    "准提佛母": [],
    "冥應公": [],
    "冥漠公": [],
    "倪府聖公爺": [],
    "倪府王爺": [],
    "倪府大人": [],
    "倪府千歲": [],
    "香山祖師": [],
    "飛像四將軍": [],
    "飛天大聖": [],
    "飛天大將": [],
    "風神爺": [],
    "陌姓公陌姓婆": [],
    "茅府千歲": [],
    "茄苳王公": [],
    "茄正公": [],
    "范府千歲": [],
    "范王公": [],
    "范元帥": [],
    "英靈祖師": [],
    "英豪祖師": [],
    "英雄公": [],
    "苓府千歲": [],
    "胡將軍": [],
    "紀府千歲": [],
    "紀王爺": [],
    "紀大帝": [],
    "秋香尊神": [],
    "省城隍爺": [],
    "皇靈地祗": [],
    "皇帝": [],
    "皇母娘娘": [],
    "皇公": [],
    "洪府王爺": [],
    "洪府元帥": [],
    "洪府千歲": [],
    "洪府二元帥": [],
    "洪先生公": [],
    "洪元帥": [],
    "泉州公": [],
    "柳星君": [],
    "柳府千歲": [],
    "查仙公": [],
    "柒府千歲": [],
    "春姑婆旋伯公": [],
    "春姑婆": [],
    "施聖王": [],
    "拾壹公": [],
    "帥爺": [],
    "帝爺公": [],
    "封府千歲": [],
    "宣靈公劉": [],
    "威靈王池府千歲": [],
    "威靈公都城隍": [],
    "威烈侯陳將軍": [],
    "威烈侯": [],
    "姜太公": [],
    "姜子牙": [],
    "姚府千歲": [],
    "姚池千歲": [],
    "城隍廟公": [],
    "城隍爺夫人": [],
    "城隍爺公祖": [],
    "城隍爺": [],
    "城隍尊神": [],
    "城隍尊王": [],
    "城隍老爺": [],
    "城隍": [],
    "南鯤鯓萬善爺公": [],
    "南嶽聖侯": [],
    "南極仙翁": [],
    "南極大帝": [],
    "南雲千歲": [],
    "南發元帥": [],
    "南無觀世音菩薩": [],
    "南無濟公禪師": [],
    "南無準提佛母": [],
    "南無千手千眼觀世音菩蕯": [],
    "南普陀佛祖": [],
    "南海觀音菩薩": [],
    "南海觀音佛祖五母娘娘": [],
    "南海觀世音菩薩": [],
    "南海觀世音佛祖": [],
    "南海佛祖": [],
    "南府鯤鯓": [],
    "南斗天神": [],
    "南天福德正神": [],
    "南天聖帝": [],
    "南天玄天上帝": [],
    "南天文衡聖帝": [],
    "勇伯公": [],
    "保儀尊王尪元帥": [],
    "保儀尊王": [],
    "保儀大夫尊王": [],
    "保儀大夫": [],
    "保安廣澤尊王": [],
    "保安尊王": [],
    "保安夫人": [],
    "保生大帝": [],
    "保生上帝": [],
    "保生二大帝": [],
    "侯府王公": [],
    "青雲仙帝": [],
    "青山靈安尊": [],
    "阿彌陀佛": [],
    "阿立祖": [],
    "長生帝君": [],
    "長生大帝": [],
    "金闕大帝": [],
    "金龍太子": [],
    "金鳳姑": [],
    "金聖公": [],
    "金童仙子": [],
    "金康元帥": [],
    "金府帝爺": [],
    "金府王爺": [],
    "金府千歲": [],
    "金李池王爺": [],
    "金池府千歲": [],
    "金吒太子": [],
    "金母娘娘": [],
    "金王爺": [],
    "金王": [],
    "金毛祖師": [],
    "金斗公": [],
    "金天元帥": [],
    "金元帥": [],
    "邱春娘": [],
    "邱府千歲": [],
    "邱王爺": [],
    "邱元帥": [],
    "舍人公": [],
    "空中萬歲": [],
    "狀元公": [],
    "牧馬侯-陳淵": [],
    "牧馬侯": [],
    "法師公": [],
    "法主聖君": [],
    "法主天君": [],
    "法主公聖君": [],
    "法主公": [],
    "法子公": [],
    "武德尊侯": [],
    "武德尊王": [],
    "武德英侯": [],
    "武德侯": [],
    "武聖關公": [],
    "武帥": [],
    "武府千歲": [],
    "武安尊王": [],
    "武安尊二王": [],
    "武安王": [],
    "林聖四帝": [],
    "林府駙馬": [],
    "林府四元帥": [],
    "林府王爺": [],
    "林府元帥": [],
    "林府千歲": [],
    "林李池府千歲": [],
    "林奶夫人": [],
    "林王爺": [],
    "林太師": [],
    "林元帥": [],
    "林女帥": [],
    "枉死城城主": [],
    "松樹尊王": [],
    "松樹王": [],
    "松府元帥": [],
    "松府千歲": [],
    "松山元帥": [],
    "杳老公": [],
    "東營元帥": [],
    "東嶽帝君": [],
    "東嶽仁聖大帝": [],
    "東嶽大帝": [],
    "東廚帝君": [],
    "東華帝君": [],
    "東陵武聖帝君": [],
    "東門王爺": [],
    "東王木公": [],
    "東方木公": [],
    "明山國王": [],
    "昊天金闕至尊玉皇大帝": [],
    "昊天大帝": [],
    "招福德武財神": [],
    "忠義聖君": [],
    "忠義將軍": [],
    "忠義烈士": [],
    "忠義宮": [],
    "忠義公碑": [],
    "忠義公元帥": [],
    "忠義公": [],
    "忠義十九公": [],
    "忠順聖王": [],
    "忠勇侯": [],
    "延平郡王": [],
    "延平邵王鄭成功": [],
    "岳隆德元帥": [],
    "岳飛元帥": [],
    "岳飛": [],
    "岳武穆王帝君": [],
    "岳武穆王": [],
    "岳府王爺": [],
    "岳府元帥": [],
    "岳府千歲": [],
    "定遠帝君趙恩主": [],
    "季府三千歲": [],
    "孟府郎君": [],
    "姑婆媽": [],
    "姑娘媽": [],
    "妮聖娘娘": [],
    "周爺公": [],
    "周黃府先鋒": [],
    "周倉聖爺": [],
    "周倉爺": [],
    "周倉大將軍": [],
    "周府將軍": [],
    "周府老爺": [],
    "周府王爺": [],
    "周府元帥": [],
    "周府大帝": [],
    "周府千歲": [],
    "周文王": [],
    "周大王": [],
    "協天聖帝": [],
    "協天大帝": [],
    "協天上帝": [],
    "里主尊王爺": [],
    "里主尊王": [],
    "邪府王爺": [],
    "邢府王爺": [],
    "邢府千歲": [],
    "邢王爺": [],
    "邢王": [],
    "良崗尊王": [],
    "甫奄公": [],
    "狄府千歲": [],
    "灶君爺": [],
    "沈元帥": [],
    "汾陽王郭子儀": [],
    "步道祖師": [],
    "杜府千歲": [],
    "李鐵拐大仙翁": [],
    "李鐵拐": [],
    "李廣將軍": [],
    "李靖托塔天王": [],
    "李將軍": [],
    "李府尊王": [],
    "李府將軍爺": [],
    "李府將軍": [],
    "李府仙祖": [],
    "李府王爺": [],
    "李府元帥": [],
    "李府千歲": [],
    "李府三尊王": [],
    "李府三元帥": [],
    "李府三千歲": [],
    "李姑娘": [],
    "李江將軍": [],
    "李托塔大王": [],
    "李光前將軍": [],
    "李伍府千歲": [],
    "李仙祖": [],
    "李王爺": [],
    "李王": [],
    "李太白金星": [],
    "李天王": [],
    "李元帥": [],
    "巫府千歲": [],
    "岑府大使": [],
    "尪元帥": [],
    "宋江爺": [],
    "孚佑帝君": [],
    "呂洞賓": [],
    "呂府千歲": [],
    "呂仙祖師": [],
    "呂仙祖": [],
    "吳鳳公": [],
    "吳將軍": [],
    "吳府王爺": [],
    "吳府元帥": [],
    "吳府千歲": [],
    "吳府三王爺": [],
    "吳府三王": [],
    "吳府三千歲": [],
    "吳必力": [],
    "吳公真仙": [],
    "助順將軍": [],
    "利眾公": [],
    "余慈爺公": [],
    "余府元帥": [],
    "余府千歲": [],
    "余仙祖": [],
    "何府千歲": [],
    "何仙姑": [],
    "伽藍爺": [],
    "伽藍尊神": [],
    "伽藍尊王": [],
    "伽藍千歲": [],
    "伯聖尊王": [],
    "伯公神像": [],
    "西嶽大帝": [],
    "西蓁荖千歲": [],
    "西極天王": [],
    "西秦老王爺": [],
    "西秦王爺": [],
    "西王瑤池金母": [],
    "西王聖母": [],
    "西王國母娘娘": [],
    "西王金母娘娘": [],
    "西王金母": [],
    "西方元帥": [],
    "西方三聖": [],
    "西天真人地藏王公": [],
    "西天佛祖": [],
    "西天老母": [],
    "老賽公佛": [],
    "老頭將軍": [],
    "老頭大王": [],
    "老鼠礁大王": [],
    "老仙公": [],
    "老大公": [],
    "竹仔腳祖": [],
    "百靈王公": [],
    "百姓公福德正神": [],
    "百姓公媽": [],
    "百姓公": [],
    "池張李府千歲": [],
    "池府老千歲": [],
    "池府四公子爺": [],
    "池府王爺": [],
    "池府元帥": [],
    "池府千歲": [],
    "池府三千歲": [],
    "池朱府千歲": [],
    "池王爺": [],
    "池王": [],
    "池.池.吳府王爺": [],
    "江府太師": [],
    "江府千歲": [],
    "江元帥": [],
    "朱薛彭三府王爺": [],
    "朱孫吳三府王爺": [],
    "朱府親王爺": [],
    "朱府李府池府三府王爺": [],
    "朱府王爺": [],
    "朱府大王爺": [],
    "朱府千歲金母娘娘": [],
    "朱府千歲": [],
    "朱府三王爺": [],
    "朱府二王爺": [],
    "朱府二千歲": [],
    "朱李金王爺": [],
    "朱李池吳范五府王爺": [],
    "朱李池王爺": [],
    "朱李池王府王爺": [],
    "朱李池千歲": [],
    "朱李池三府王爺": [],
    "朱吳清三府王爺": [],
    "朱池李千歲": [],
    "朱池李三王爺": [],
    "朱池李三千歲": [],
    "朱刑李三王爺": [],
    "朱刑李三千歲": [],
    "朱伍府千歲": [],
    "朱王爺": [],
    "朱王": [],
    "朱公一貴": [],
    "朱子公": [],
    "朱大姐": [],
    "有應公婆土地公": [],
    "有應公": [],
    "托塔天王李靖": [],
    "安溪董公真人": [],
    "安溪三城隍爺": [],
    "安海三城隍": [],
    "宇宙母娘": [],
    "宇宙三祖": [],
    "如意娘娘": [],
    "如來佛祖": [],
    "好漢爺": [],
    "好漢公": [],
    "好漢大將軍": [],
    "地藏王菩薩": [],
    "地藏王": [],
    "地基主": [],
    "地母尊神": [],
    "地母娘娘": [],
    "地母至尊": [],
    "地母": [],
    "吉府王爺": [],
    "吉府千歲": [],
    "刑府大人": [],
    "刑府千歲": [],
    "刑王爺": [],
    "刑天王爺": [],
    "共王公夫人媽": [],
    "先生公": [],
    "先代公": [],
    "伏魔公": [],
    "伏魔大將軍": [],
    "伏魔大帝": [],
    "伏羲先帝": [],
    "伏羲氏神農氏軒轅氏": [],
    "伏羲氏": [],
    "伏羲大帝": [],
    "伏羲八卦祖師": [],
    "伍顯大帝": [],
    "伍聖天尊": [],
    "伍恩主公": [],
    "伍府恩主公": [],
    "伍府千歲": [],
    "伍佛祖": [],
    "伍年千歲": [],
    "任聖公": [],
    "石靈大帝": [],
    "石頭公王": [],
    "石頭公": [],
    "石聖爺": [],
    "石碑": [],
    "石明仙祖": [],
    "石府元帥": [],
    "石府千歲": [],
    "石車公": [],
    "石太保": [],
    "石公": [],
    "白靈公": [],
    "白將軍": [],
    "白馬尊王": [],
    "白馬文武大王": [],
    "白馬大王": [],
    "白府代天巡狩": [],
    "白府千歲": [],
    "白衣祖師": [],
    "白王爺": [],
    "白少爺": [],
    "田督元帥": [],
    "田都元帥爺": [],
    "田都元帥": [],
    "田島千歲": [],
    "田府元帥": [],
    "田府千歲": [],
    "田元帥": [],
    "田中將軍": [],
    "甘露神": [],
    "玉龍尊王": [],
    "玉皇太子": [],
    "玉皇公主": [],
    "玉皇大帝佛尊": [],
    "玉皇大帝": [],
    "玉皇大天尊玄靈高上帝": [],
    "玉皇大天尊": [],
    "玉皇上帝": [],
    "玉皇三宮主": [],
    "玉皇三公主娘娘": [],
    "玉王千歲": [],
    "玉天大帝": [],
    "玉天三大子": [],
    "玉女娘娘": [],
    "玉二聖母": [],
    "玄壇公": [],
    "玄壇元帥": [],
    "玄德聖帝": [],
    "玄玄上人": [],
    "玄天高上帝": [],
    "玄天真武大帝": [],
    "玄天北極上帝": [],
    "玄天大帝": [],
    "玄天上帝觀音佛祖": [],
    "玄天上帝趙李元帥": [],
    "玄天上帝爺": [],
    "玄天上帝包府千歲關聖帝君": [],
    "玄天上帝中壇元帥": [],
    "玄天上帝": [],
    "民主公王爺": [],
    "民主千歲": [],
    "正義公": [],
    "正官正王": [],
    "正一張府天師": [],
    "正一天師": [],
    "本埔八卦福神像": [],
    "本府將軍": [],
    "本官公": [],
    "平水尊王": [],
    "平水天王": [],
    "布伯公": [],
    "巧聖先師": [],
    "巧聖仙師": [],
    "四面金剛佛": [],
    "四面佛": [],
    "四城隍": [],
    "四府將軍": [],
    "四府王爺": [],
    "四府千歲": [],
    "四十九公": [],
    "司命真君": [],
    "司命灶君": [],
    "台灣天下都城隍": [],
    "古公三聖": [],
    "古公三王": [],
    "北嶽大帝": [],
    "北極真武老祖": [],
    "北極先天朱王": [],
    "北極玄天真武上帝": [],
    "北極玄天六帝": [],
    "北極玄天上帝": [],
    "北極大帝": [],
    "北極上帝": [],
    "北港媽祖": [],
    "北海道公": [],
    "北府五王": [],
    "北方真武上帝": [],
    "北斗星君": [],
    "包蕭雷三府王爺": [],
    "包青天": [],
    "包府千歲": [],
    "包王爺": [],
    "包公聖祖": [],
    "包公尊主": [],
    "出軍公元師": [],
    "代天法主": [],
    "代天巡狩": [],
    "代天下界公": [],
    "仙姑媽": [],
    "仙姑娘媽": [],
    "仙姑娘": [],
    "仙姑": [],
    "仙公媽": [],
    "仙公至尊": [],
    "仙公": [],
    "主母娘娘": [],
    "王靈天君": [],
    "王禪老祖": [],
    "王勳千歲": [],
    "王爺宮": [],
    "王爺太子爺": [],
    "王爺公": [],
    "王爺": [],
    "王媽娘娘": [],
    "王恩公": [],
    "王孫大使": [],
    "王府老爺": [],
    "王府仙師": [],
    "王府元帥": [],
    "王府大使": [],
    "王府千歲": [],
    "王府三千歲": [],
    "王老仙師": [],
    "王先生": [],
    "王母娘娘金府千歲關聖帝君": [],
    "王母娘娘玉皇上帝": [],
    "王母娘娘": [],
    "王仙姑": [],
    "王天君": [],
    "王公": [],
    "王大姊": [],
    "水遷尊王": [],
    "水德聖君": [],
    "水德星君": [],
    "水僊尊王": [],
    "水部尚書公": [],
    "水流公": [],
    "水尾公": [],
    "水吉成公": [],
    "水仙尊王": [],
    "水仙王": [],
    "木吒二太子": [],
    "月姑娘娘": [],
    "月下老人": [],
    "方府千歲": [],
    "方仙姑": [],
    "斗姥元君": [],
    "文衡關聖帝君": [],
    "文衡聖帝": [],
    "文衡聖君": [],
    "文衡帝君": [],
    "文賢聖帝": [],
    "文聖帝君": [],
    "文財神": [],
    "文海小城隍爺": [],
    "文殊菩薩": [],
    "文相公": [],
    "文武尊王": [],
    "文武城隍公": [],
    "文武大眾爺": [],
    "文昌帝君": [],
    "文尼真佛": [],
    "尤府千歲": [],
    "孔德尊王": [],
    "孔明先聖": [],
    "孔府千歲": [],
    "夫人媽": [],
    "太陽神君": [],
    "太陽星君太陰娘娘": [],
    "太陽星君": [],
    "太陽公": [],
    "太祖": [],
    "太師爺": [],
    "太白神君": [],
    "太白金星": [],
    "太白金仙": [],
    "太元聖母": [],
    "太元老母": [],
    "太子爺": [],
    "太子太保": [],
    "太子元帥": [],
    "太子中壇元帥": [],
    "太上道德天尊": [],
    "太上道祖": [],
    "太上李老君": [],
    "太上老君": [],
    "太上元始天尊": [],
    "太乙救苦天尊": [],
    "太乙真人": [],
    "天艶公主": [],
    "天羅至尊": [],
    "天遷五帝": [],
    "天極上帝": [],
    "天僊伍帝": [],
    "天符神": [],
    "天神爺開天聖王朱李池三千歲": [],
    "天師大帝": [],
    "天府王爺楊府五使池府千歲": [],
    "天府王爺": [],
    "天官武財神": [],
    "天官文財神": [],
    "天官五路武財神無完財神尊": [],
    "天官五路武財神": [],
    "天官大帝": [],
    "天宋媽": [],
    "天仙府大帝": [],
    "天王聖帝公": [],
    "天水夫人": [],
    "天上聖母溫府千歲": [],
    "天上聖母媽祖": [],
    "天上聖母娘娘": [],
    "天上聖母老六媽祖": [],
    "天上聖母老大媽": [],
    "天上聖母北極玄天上帝": [],
    "天上聖母王母娘娘": [],
    "天上聖母太子觀音佛祖": [],
    "天上聖母五年千歲五府千歲": [],
    "天上聖母三令聖母": [],
    "天上聖母": [],
    "天上主宰大原靈聖位": [],
    "天上王母娘娘": [],
    "天上三聖母": [],
    "友聖公": [],
    "六將尊神": [],
    "六堆民眾之忠勇烈士": [],
    "六桂宗祖": [],
    "六根莊萬應公": [],
    "六房天上聖母": [],
    "六府千歲": [],
    "六姓府王爺": [],
    "六使公": [],
    "六位尊王": [],
    "公王": [],
    "公子爺": [],
    "元帥爺公": [],
    "元帥爺": [],
    "元帥": [],
    "元始天尊": [],
    "元始天王": [],
    "元天上帝": [],
    "仁聖大帝": [],
    "什三王爺": [],
    "井邊將軍": [],
    "五靈公": [],
    "五顯靈官華光大帝": [],
    "五顯靈官大帝": [],
    "五顯大帝.媽祖": [],
    "五顯大帝": [],
    "五顯三大帝": [],
    "五嶽大帝": [],
    "五龍真君": [],
    "五穀聖帝": [],
    "五穀爺": [],
    "五穀神農大帝": [],
    "五穀神農": [],
    "五穀先帝": [],
    "五穀仙帝": [],
    "五穀大帝": [],
    "五瘟大帝": [],
    "五福神": [],
    "五福天仙": [],
    "五福大帝": [],
    "五榖神農大帝": [],
    "五榖先帝": [],
    "五榖王": [],
    "五雷元帥": [],
    "五路財神": [],
    "五聖恩主公": [],
    "五聖千歲": [],
    "五極大帝": [],
    "五尊恩祖": [],
    "五尊恩主": [],
    "五尊恩王": [],
    "五恩主": [],
    "五毒神": [],
    "五虎將": [],
    "五府將軍": [],
    "五府池千歲": [],
    "五府王爺": [],
    "五府元帥": [],
    "五府千歲天上聖母": [],
    "五府千歲及三清道祖": [],
    "五府千歲": [],
    "五府三千歲": [],
    "五姓公": [],
    "五谷聖帝": [],
    "五谷神農皇帝": [],
    "五谷神農大帝": [],
    "五谷神帝": [],
    "五谷先帝": [],
    "五谷仙帝": [],
    "五谷大帝": [],
    "五行財神": [],
    "五老大天尊": [],
    "五年王": [],
    "五年千歲": [],
    "五主王爺": [],
    "五王爺": [],
    "五王代天巡守": [],
    "五王千歲": [],
    "五王": [],
    "五文昌帝君": [],
    "五文昌夫子五年千歲": [],
    "五夫人媽": [],
    "五天聖帝": [],
    "五六府千歲": [],
    "五公禪師": [],
    "五公菩薩": [],
    "五十三將軍": [],
    "五十人公": [],
    "中壇玄師": [],
    "中壇太子元帥": [],
    "中壇太子": [],
    "中壇元帥": [],
    "中軍府": [],
    "中軍元帥": [],
    "中央混元真母靈源天尊": [],
    "中元普渡公": [],
    "山西夫子": [],
    "山有神君": [],
    "山王聖君": [],
    "小祖娘媽": [],
    "子龍爺": [],
    "女媧娘神":["女媧娘娘", "女媧娘"],
    "大鵬鳥元帥": [],
    "大樹公": [],
    "大德禪師": [],
    "大寮伯": [],
    "大聖爺公": [],
    "大聖爺": [],
    "大聖公媽": [],
    "大聖公": [],
    "大眾爺地藏王": [],
    "大眾爺公": [],
    "大眾爺": [],
    "大眾媽神": [],
    "大眾媽": [],
    "大眾公": [],
    "大眾千歲": [],
    "大將爺公": [],
    "大將爺": [],
    "大將公": [],
    "大國尊王": [],
    "大夏聖帝": [],
    "大坵白馬大王": [],
    "大使爺": [],
    "大宋太后娘娘": [],
    "大宋三忠王": [],
    "大伯爺介子推": [],
    "大伯爺": [],
    "大王爺": [],
    "大士爺": [],
    "大二使爺": [],
    "土地伯公": [],
    "土地正神": ["土地公"],
    "土地公婆": [],
    "土地公土地婆": [],
    "土地元帥": [],
    "千歲爺": [],
    "千眾爺": [],
    "千軍萬馬帥": [],
    "千秋爺": [],
    "千手千眼觀音": [],
    "下元水官大帝": [],
    "上帝爺公": [],
    "上帝爺": [],
    "上帝公": [],
    "三寶佛祖": [],
    "三寶佛": [],
    "三藍祖師": [],
    "三輪菩薩": [],
    "三聖爺": [],
    "三聖恩主": [],
    "三聖佛": [],
    "三聖公": [],
    "三聖大帝": [],
    "三媽佛祖": [],
    "三尊恩主": [],
    "三尊恩王": [],
    "三尊大帝": [],
    "三善公": [],
    "三魚王": [],
    "三清道祖": [],
    "三清祖師": [],
    "三教佛祖": [],
    "三恩主公": [],
    "三恩主": [],
    "三界公": [],
    "三帥夫人": [],
    "三品夫人": [],
    "三侯郡馬千歲": [],
    "三法師": [],
    "三法司": [],
    "三法王": [],
    "三法大將軍": [],
    "三忠公": [],
    "三府王爺.天上聖母": [],
    "三府王爺": [],
    "三府元帥": [],
    "三府千歲": [],
    "三府三王公": [],
    "三岳大帝": [],
    "三官大帝三山國王": [],
    "三官大帝": [],
    "三姓尊王": [],
    "三姓公": [],
    "三姑娘娘": [],
    "三姑娘": [],
    "三坪祖師爺": [],
    "三坪祖師公": [],
    "三坪祖師": [],
    "三君子": [],
    "三位夫人": [],
    "三老爺": [],
    "三光": [],
    "三田都千歲": [],
    "三平祖師": [],
    "三奶娘": [],
    "三奶夫人媽": [],
    "三奶夫人": [],
    "三令聖母": [],
    "三代祖師": [],
    "三代公": [],
    "三仙國王": [],
    "三仙元師": [],
    "三仙女": [],
    "三王爺": [],
    "三王太歲": [],
    "三王公": [],
    "三太子爺": [],
    "三太子": [],
    "三元真君": [],
    "三元帥": [],
    "三元三品三官大帝": [],
    "三山護國國王": [],
    "三山國王": [],
    "三子王爺": [],
    "三千歲": [],
    "三十六天罡": [],
    "三一教主": [],
    "十三名義民": [],
    "十八羅漢尊者": [],
    "十八義民": [],
    "十八王公": [],
    "十二瘟王千歲": [],
    "十二瘟王": [],
    "十二延天溪女娘娘": [],
    "八德公": [],
    "八聖娘娘": [],
    "八卦祖師": [],
    "八仙": [],
    "人頭爺": [],
    "二路元帥": [],
    "二郎神君": [],
    "二府王爺": [],
    "二姑娘媽": [],
    "二王公": [],
    "二元帥": [],
    "九龍觀世音菩薩": [],
    "九龍魏府三公爺": [],
    "九龍殿下": [],
    "九龍三公": [],
    "九蓮佛祖": [],
    "九聖帝": [],
    "九郎公神龕": [],
    "九皇大帝": [],
    "九府仙師": [],
    "九府王爺": [],
    "九府千歲": [],
    "九天尊王": [],
    "九天真王": [],
    "九天娘娘": [],
    "九天玄母": [],
    "九天玄女娘娘": [],
    "九天玄女仙師": [],
    "九天玄女": [],
    "九天玄九菩薩": [],
    "九天中壇元帥": [],
    "九天三聖帝": [],
    "七將軍爺": [],
    "七將軍": [],
    "七祖仙師": [],
    "七娘媽": [],
    "七省大元帥": [],
    "七星娘娘": [],
    "七府王爺": [],
    "七府千歲": [],
    "七姓公王爺": [],
    "七仙姑": [],
    "七主王爺": [],
    "七夫人媽": [],
    "丁軍爺": [],
    "丁府王爺": [],
    "丁府元帥": [],
    "丁府千歲": [],
    "丁府八千歲": [],
    "一將二軍":[]
}